odoo/addons/auth_jwt_server_env/README.rst
odoo/addons/auth_jwt_server_env/__init__.py
odoo/addons/auth_jwt_server_env/__manifest__.py
odoo/addons/auth_jwt_server_env/i18n/auth_jwt_server_env.pot
odoo/addons/auth_jwt_server_env/i18n/it.po
odoo/addons/auth_jwt_server_env/models/__init__.py
odoo/addons/auth_jwt_server_env/models/auth_jwt_validator.py
odoo/addons/auth_jwt_server_env/readme/CONTRIBUTORS.rst
odoo/addons/auth_jwt_server_env/readme/DESCRIPTION.rst
odoo/addons/auth_jwt_server_env/static/description/icon.png
odoo/addons/auth_jwt_server_env/static/description/index.html
odoo_addon_auth_jwt_server_env-16.0.1.0.0.5.dist-info/METADATA
odoo_addon_auth_jwt_server_env-16.0.1.0.0.5.dist-info/WHEEL
odoo_addon_auth_jwt_server_env-16.0.1.0.0.5.dist-info/top_level.txt
odoo_addon_auth_jwt_server_env-16.0.1.0.0.5.dist-info/RECORD
