Metadata-Version: 2.1
Name: odoo-addon-auth_jwt_server_env
Version: 16.0.1.0.0.5
Summary: This addon adds auth.jwt.validator fields to server env
Home-page: https://github.com/OCA/server-auth
Author: ACSONE SA/NV, Odoo Community Association (OCA)
Author-email: support@odoo-community.org
License: AGPL-3
Classifier: Programming Language :: Python
Classifier: Framework :: Odoo
Classifier: Framework :: Odoo :: 16.0
Classifier: License :: OSI Approved :: GNU Affero General Public License v3
Requires-Python: >=3.10
Requires-Dist: odoo-addon-auth-jwt<16.1dev,>=16.0dev
Requires-Dist: odoo-addon-server-environment<16.1dev,>=16.0dev
Requires-Dist: odoo<16.1dev,>=16.0a
